MANIFEST.in
README.md
setup.cfg
setup.py
django_term.egg-info/PKG-INFO
django_term.egg-info/SOURCES.txt
django_term.egg-info/dependency_links.txt
django_term.egg-info/not-zip-safe
django_term.egg-info/requires.txt
django_term.egg-info/top_level.txt
term/__init__.py
term/admin.py
term/apps.py
term/commands.py
term/conf.py
term/models.py
term/tests.py
term/urls.py
term/views.py
term/migrations/__init__.py
term/migrations/__pycache__/__init__.cpython-35.pyc
term/migrations/__pycache__/__init__.cpython-36.pyc
term/static/css/terminal.css
term/static/js/axios.min.js
term/static/js/vue.js
term/static/js/vue.min.js
term/static/js/vuex.js
term/static/js/vv.js
term/static/js/vv.min.js
term/static/js/vvstore.js
term/templates/term/app.js
term/templates/term/colors.css
term/templates/term/handlers.js
term/templates/term/head.html
term/templates/term/index.html
term/templatetags/__init__.py
term/templatetags/__init__.pyc
term/templatetags/terminal_tags.py
term/templatetags/__pycache__/__init__.cpython-35.pyc
term/templatetags/__pycache__/__init__.cpython-36.pyc
term/templatetags/__pycache__/dex_tags.cpython-35.pyc
term/templatetags/__pycache__/instant_tags.cpython-35.pyc
term/templatetags/__pycache__/terminal_tags.cpython-35.pyc
term/templatetags/__pycache__/terminal_tags.cpython-36.pyc
term/terminal/commands.py
term/terminal/__pycache__/commands.cpython-35.pyc
term/terminal/__pycache__/commands.cpython-36.pyc