Metadata-Version: 1.1
Name: django-term
Version: 0.2
Summary: In browser term for Django 
Home-page: https://github.com/synw/django-term
Author: synw
Author-email: synwe@yahoo.com
License: UNKNOWN
Download-URL: https://github.com/synw/django-term/releases/tag/0.2
Keywords: django,terminal
Platform: UNKNOWN
Classifier: Development Status :: 3 - Alpha
Classifier: Framework :: Django :: 1.11
Classifier: Intended Audience :: Developers
Classifier: License :: OSI Approved :: MIT License
Classifier: Programming Language :: Python :: 3.6
